Workbook

Sheet Dashboard
B2: 2026 Business Budget
B3: Annual Overview | Jan 2026 - Dec 2026 | Payroll Semi-monthly (15th & Last day) | Northwind Studio LLC
B5: REVENUE | D5: EXPENSES | F5: NET PROFIT | H5: PROFIT MARGIN | K5: AVG MONTHLY BURN | M5: PAYROLL RUNS
B6: =D42 | D6: =G42 | F6: =H42 | H6: =IFERROR(H42/D42,0) | K6: =G42/12 | M6: =C42
B7: earned this year | D7: fixed + variable | F7: revenue - expenses | H7: of revenue kept | K7: expenses / 12 | M7: payroll dates this year
B28: Monthly Breakdown | K28: Expenses by Category
B29: Month | C29: Payroll Runs | D29: Revenue | E29: Fixed | F29: Variable | G29: Total Expenses | H29: Net Profit | I29: Margin | K29: Category | L29: Annual | M29: Monthly Avg | N29: % of Expenses
B30: 46023 | C30: =COUNTIFS('Payroll'!$D$6:$D$35,B30) | D30: ='Revenue'!D21 | E30: =SUMIFS('Expenses'!$F$6:$F$66,'Expenses'!$D$6:$D$66,"Fixed") | F30: =SUMIFS('Expenses'!$F$6:$F$66,'Expenses'!$D$6:$D$66,"Variable") | G30: =E30+F30 | H30: =D30-G30 | I30: =IFERROR(H30/D30,0) | K30: Payroll | L30: =SUMIF('Expenses'!$C$6:$C$66,K30,'Expenses'!$R$6:$R$66) | M30: =L30/12 | N30: =IFERROR(L30/$L$47,0)
B31: 46054 | C31: =COUNTIFS('Payroll'!$D$6:$D$35,B31) | D31: ='Revenue'!E21 | E31: =SUMIFS('Expenses'!$G$6:$G$66,'Expenses'!$D$6:$D$66,"Fixed") | F31: =SUMIFS('Expenses'!$G$6:$G$66,'Expenses'!$D$6:$D$66,"Variable") | G31: =E31+F31 | H31: =D31-G31 | I31: =IFERROR(H31/D31,0) | K31: Rent & Facilities | L31: =SUMIF('Expenses'!$C$6:$C$66,K31,'Expenses'!$R$6:$R$66) | M31: =L31/12 | N31: =IFERROR(L31/$L$47,0)
B32: 46082 | C32: =COUNTIFS('Payroll'!$D$6:$D$35,B32) | D32: ='Revenue'!F21 | E32: =SUMIFS('Expenses'!$H$6:$H$66,'Expenses'!$D$6:$D$66,"Fixed") | F32: =SUMIFS('Expenses'!$H$6:$H$66,'Expenses'!$D$6:$D$66,"Variable") | G32: =E32+F32 | H32: =D32-G32 | I32: =IFERROR(H32/D32,0) | K32: Utilities | L32: =SUMIF('Expenses'!$C$6:$C$66,K32,'Expenses'!$R$6:$R$66) | M32: =L32/12 | N32: =IFERROR(L32/$L$47,0)
B33: 46113 | C33: =COUNTIFS('Payroll'!$D$6:$D$35,B33) | D33: ='Revenue'!G21 | E33: =SUMIFS('Expenses'!$I$6:$I$66,'Expenses'!$D$6:$D$66,"Fixed") | F33: =SUMIFS('Expenses'!$I$6:$I$66,'Expenses'!$D$6:$D$66,"Variable") | G33: =E33+F33 | H33: =D33-G33 | I33: =IFERROR(H33/D33,0) | K33: Software & Subscriptions | L33: =SUMIF('Expenses'!$C$6:$C$66,K33,'Expenses'!$R$6:$R$66) | M33: =L33/12 | N33: =IFERROR(L33/$L$47,0)
B34: 46143 | C34: =COUNTIFS('Payroll'!$D$6:$D$35,B34) | D34: ='Revenue'!H21 | E34: =SUMIFS('Expenses'!$J$6:$J$66,'Expenses'!$D$6:$D$66,"Fixed") | F34: =SUMIFS('Expenses'!$J$6:$J$66,'Expenses'!$D$6:$D$66,"Variable") | G34: =E34+F34 | H34: =D34-G34 | I34: =IFERROR(H34/D34,0) | K34: Marketing & Advertising | L34: =SUMIF('Expenses'!$C$6:$C$66,K34,'Expenses'!$R$6:$R$66) | M34: =L34/12 | N34: =IFERROR(L34/$L$47,0)
B35: 46174 | C35: =COUNTIFS('Payroll'!$D$6:$D$35,B35) | D35: ='Revenue'!I21 | E35: =SUMIFS('Expenses'!$K$6:$K$66,'Expenses'!$D$6:$D$66,"Fixed") | F35: =SUMIFS('Expenses'!$K$6:$K$66,'Expenses'!$D$6:$D$66,"Variable") | G35: =E35+F35 | H35: =D35-G35 | I35: =IFERROR(H35/D35,0) | K35: Inventory / COGS | L35: =SUMIF('Expenses'!$C$6:$C$66,K35,'Expenses'!$R$6:$R$66) | M35: =L35/12 | N35: =IFERROR(L35/$L$47,0)
B36: 46204 | C36: =COUNTIFS('Payroll'!$D$6:$D$35,B36) | D36: ='Revenue'!J21 | E36: =SUMIFS('Expenses'!$L$6:$L$66,'Expenses'!$D$6:$D$66,"Fixed") | F36: =SUMIFS('Expenses'!$L$6:$L$66,'Expenses'!$D$6:$D$66,"Variable") | G36: =E36+F36 | H36: =D36-G36 | I36: =IFERROR(H36/D36,0) | K36: Contractors | L36: =SUMIF('Expenses'!$C$6:$C$66,K36,'Expenses'!$R$6:$R$66) | M36: =L36/12 | N36: =IFERROR(L36/$L$47,0)
B37: 46235 | C37: =COUNTIFS('Payroll'!$D$6:$D$35,B37) | D37: ='Revenue'!K21 | E37: =SUMIFS('Expenses'!$M$6:$M$66,'Expenses'!$D$6:$D$66,"Fixed") | F37: =SUMIFS('Expenses'!$M$6:$M$66,'Expenses'!$D$6:$D$66,"Variable") | G37: =E37+F37 | H37: =D37-G37 | I37: =IFERROR(H37/D37,0) | K37: Supplies | L37: =SUMIF('Expenses'!$C$6:$C$66,K37,'Expenses'!$R$6:$R$66) | M37: =L37/12 | N37: =IFERROR(L37/$L$47,0)
B38: 46266 | C38: =COUNTIFS('Payroll'!$D$6:$D$35,B38) | D38: ='Revenue'!L21 | E38: =SUMIFS('Expenses'!$N$6:$N$66,'Expenses'!$D$6:$D$66,"Fixed") | F38: =SUMIFS('Expenses'!$N$6:$N$66,'Expenses'!$D$6:$D$66,"Variable") | G38: =E38+F38 | H38: =D38-G38 | I38: =IFERROR(H38/D38,0) | K38: Insurance | L38: =SUMIF('Expenses'!$C$6:$C$66,K38,'Expenses'!$R$6:$R$66) | M38: =L38/12 | N38: =IFERROR(L38/$L$47,0)
B39: 46296 | C39: =COUNTIFS('Payroll'!$D$6:$D$35,B39) | D39: ='Revenue'!M21 | E39: =SUMIFS('Expenses'!$O$6:$O$66,'Expenses'!$D$6:$D$66,"Fixed") | F39: =SUMIFS('Expenses'!$O$6:$O$66,'Expenses'!$D$6:$D$66,"Variable") | G39: =E39+F39 | H39: =D39-G39 | I39: =IFERROR(H39/D39,0) | K39: Professional Fees | L39: =SUMIF('Expenses'!$C$6:$C$66,K39,'Expenses'!$R$6:$R$66) | M39: =L39/12 | N39: =IFERROR(L39/$L$47,0)
B40: 46327 | C40: =COUNTIFS('Payroll'!$D$6:$D$35,B40) | D40: ='Revenue'!N21 | E40: =SUMIFS('Expenses'!$P$6:$P$66,'Expenses'!$D$6:$D$66,"Fixed") | F40: =SUMIFS('Expenses'!$P$6:$P$66,'Expenses'!$D$6:$D$66,"Variable") | G40: =E40+F40 | H40: =D40-G40 | I40: =IFERROR(H40/D40,0) | K40: Travel & Meals | L40: =SUMIF('Expenses'!$C$6:$C$66,K40,'Expenses'!$R$6:$R$66) | M40: =L40/12 | N40: =IFERROR(L40/$L$47,0)
B41: 46357 | C41: =COUNTIFS('Payroll'!$D$6:$D$35,B41) | D41: ='Revenue'!O21 | E41: =SUMIFS('Expenses'!$Q$6:$Q$66,'Expenses'!$D$6:$D$66,"Fixed") | F41: =SUMIFS('Expenses'!$Q$6:$Q$66,'Expenses'!$D$6:$D$66,"Variable") | G41: =E41+F41 | H41: =D41-G41 | I41: =IFERROR(H41/D41,0) | K41: Equipment | L41: =SUMIF('Expenses'!$C$6:$C$66,K41,'Expenses'!$R$6:$R$66) | M41: =L41/12 | N41: =IFERROR(L41/$L$47,0)
B42: TOTAL | C42: =SUM(C30:C41) | D42: =SUM(D30:D41) | E42: =SUM(E30:E41) | F42: =SUM(F30:F41) | G42: =SUM(G30:G41) | H42: =SUM(H30:H41) | I42: =IFERROR(H42/D42,0) | K42: Taxes & Licenses | L42: =SUMIF('Expenses'!$C$6:$C$66,K42,'Expenses'!$R$6:$R$66) | M42: =L42/12 | N42: =IFERROR(L42/$L$47,0)
K43: Bank & Merchant Fees | L43: =SUMIF('Expenses'!$C$6:$C$66,K43,'Expenses'!$R$6:$R$66) | M43: =L43/12 | N43: =IFERROR(L43/$L$47,0)
K44: Loan Payments | L44: =SUMIF('Expenses'!$C$6:$C$66,K44,'Expenses'!$R$6:$R$66) | M44: =L44/12 | N44: =IFERROR(L44/$L$47,0)
K45: Owner Pay | L45: =SUMIF('Expenses'!$C$6:$C$66,K45,'Expenses'!$R$6:$R$66) | M45: =L45/12 | N45: =IFERROR(L45/$L$47,0)
K46: Other | L46: =SUMIF('Expenses'!$C$6:$C$66,K46,'Expenses'!$R$6:$R$66) | M46: =L46/12 | N46: =IFERROR(L46/$L$47,0)
K47: TOTAL | L47: =SUM(L30:L46) | M47: =SUM(M30:M46) | N47: =IF(L47>0,1,0)
B50: Reserve Goals | H50: Loans & Credit
B51: TOTAL TARGET | D51: SAVED SO FAR | F51: PROGRESS | H51: TOTAL OWED | K51: MIN PAYMENTS
B52: ='Reserve Goals'!C16 | D52: ='Reserve Goals'!D16 | F52: =IFERROR('Reserve Goals'!D16/'Reserve Goals'!C16,0) | H52: ='Loans & Credit'!C16 | K52: ='Loans & Credit'!E16
B53: across all goals | D53: toward your goals | F53: of total target | H53: current balances | K53: per month

Sheet Revenue
B2: Revenue
B3: Enter expected revenue per month for each stream. Pick a Category from the dropdown.
B5: Source | C5: Category | D5: 46023 | E5: 46054 | F5: 46082 | G5: 46113 | H5: 46143 | I5: 46174 | J5: 46204 | K5: 46235 | L5: 46266 | M5: 46296 | N5: 46327 | O5: 46357 | P5: Annual Total
B6: Client retainers | C6: Recurring / Subscriptions | D6: 14000 | E6: 14000 | F6: 14000 | G6: 14000 | H6: 14000 | I6: 14000 | J6: 14000 | K6: 14000 | L6: 14000 | M6: 14000 | N6: 14000 | O6: 14000 | P6: =IF(COUNT(D6:O6)=0,"",SUM(D6:O6))
B7: Project work | C7: Services | D7: 6000 | E7: 5000 | F7: 9000 | G7: 8000 | H7: 7000 | I7: 12000 | J7: 6000 | K7: 5000 | L7: 9000 | M7: 11000 | N7: 14000 | O7: 8000 | P7: =IF(COUNT(D7:O7)=0,"",SUM(D7:O7))
B8: Template shop | C8: Product Sales | D8: 1200 | E8: 1200 | F8: 1200 | G8: 1200 | H8: 1200 | I8: 1200 | J8: 1200 | K8: 1200 | L8: 1200 | M8: 1200 | N8: 1200 | O8: 1200 | P8: =IF(COUNT(D8:O8)=0,"",SUM(D8:O8))
P9: =IF(COUNT(D9:O9)=0,"",SUM(D9:O9))
P10: =IF(COUNT(D10:O10)=0,"",SUM(D10:O10))
P11: =IF(COUNT(D11:O11)=0,"",SUM(D11:O11))
P12: =IF(COUNT(D12:O12)=0,"",SUM(D12:O12))
P13: =IF(COUNT(D13:O13)=0,"",SUM(D13:O13))
P14: =IF(COUNT(D14:O14)=0,"",SUM(D14:O14))
P15: =IF(COUNT(D15:O15)=0,"",SUM(D15:O15))
P16: =IF(COUNT(D16:O16)=0,"",SUM(D16:O16))
P17: =IF(COUNT(D17:O17)=0,"",SUM(D17:O17))
P18: =IF(COUNT(D18:O18)=0,"",SUM(D18:O18))
P19: =IF(COUNT(D19:O19)=0,"",SUM(D19:O19))
P20: =IF(COUNT(D20:O20)=0,"",SUM(D20:O20))
B21: TOTAL REVENUE | D21: =SUM(D6:D20) | E21: =SUM(E6:E20) | F21: =SUM(F6:F20) | G21: =SUM(G6:G20) | H21: =SUM(H6:H20) | I21: =SUM(I6:I20) | J21: =SUM(J6:J20) | K21: =SUM(K6:K20) | ... P21: =SUM(P6:P20)

Sheet Payroll
B2: Payroll Calendar
B3: Every payroll date in your budget period. Enter the total cost of each run (wages, taxes, benefits).
B5: # | C5: Payroll Date | D5: Month | E5: Payroll Cost | F5: Notes
B6: 1 | C6: 46037 | D6: =IF(C6="","",DATE(YEAR(C6),MONTH(C6),1)) | E6: 6800
B7: 2 | C7: 46053 | D7: =IF(C7="","",DATE(YEAR(C7),MONTH(C7),1)) | E7: 6800
B8: 3 | C8: 46068 | D8: =IF(C8="","",DATE(YEAR(C8),MONTH(C8),1)) | E8: 6800
B9: 4 | C9: 46081 | D9: =IF(C9="","",DATE(YEAR(C9),MONTH(C9),1)) | E9: 6800
B10: 5 | C10: 46096 | D10: =IF(C10="","",DATE(YEAR(C10),MONTH(C10),1)) | E10: 6800
B11: 6 | C11: 46112 | D11: =IF(C11="","",DATE(YEAR(C11),MONTH(C11),1)) | E11: 6800
B12: 7 | C12: 46127 | D12: =IF(C12="","",DATE(YEAR(C12),MONTH(C12),1)) | E12: 6800
B13: 8 | C13: 46142 | D13: =IF(C13="","",DATE(YEAR(C13),MONTH(C13),1)) | E13: 6800
B14: 9 | C14: 46157 | D14: =IF(C14="","",DATE(YEAR(C14),MONTH(C14),1)) | E14: 6800
B15: 10 | C15: 46173 | D15: =IF(C15="","",DATE(YEAR(C15),MONTH(C15),1)) | E15: 6800
B16: 11 | C16: 46188 | D16: =IF(C16="","",DATE(YEAR(C16),MONTH(C16),1)) | E16: 6800
B17: 12 | C17: 46203 | D17: =IF(C17="","",DATE(YEAR(C17),MONTH(C17),1)) | E17: 6800
... B29: 24 | C29: 46387 | D29: =IF(C29="","",DATE(YEAR(C29),MONTH(C29),1)) | E29: 6800
D30: =IF(C30="","",DATE(YEAR(C30),MONTH(C30),1))
D31: =IF(C31="","",DATE(YEAR(C31),MONTH(C31),1))
D32: =IF(C32="","",DATE(YEAR(C32),MONTH(C32),1))
D33: =IF(C33="","",DATE(YEAR(C33),MONTH(C33),1))
D34: =IF(C34="","",DATE(YEAR(C34),MONTH(C34),1))
D35: =IF(C35="","",DATE(YEAR(C35),MONTH(C35),1))
B36: TOTAL | E36: =SUM(E6:E35)

Sheet Expenses
B2: Business Expenses
B3: Fixed = same every month (rent, software, payroll). Variable = changes with activity (inventory, ads). Payroll fills from the Payroll sheet.
B5: Name | C5: Category | D5: Type | E5: Due Day | F5: 46023 | G5: 46054 | H5: 46082 | I5: 46113 | J5: 46143 | K5: 46174 | L5: 46204 | M5: 46235 | N5: 46266 | O5: 46296 | P5: 46327 | Q5: 46357 | R5: Annual Total
B6: Payroll (Semi-monthly (15th & Last day)) | C6: Payroll | D6: Fixed | F6: =SUMIFS('Payroll'!$E$6:$E$35,'Payroll'!$D$6:$D$35,F$5) | G6: =SUMIFS('Payroll'!$E$6:$E$35,'Payroll'!$D$6:$D$35,G$5) | H6: =SUMIFS('Payroll'!$E$6:$E$35,'Payroll'!$D$6:$D$35,H$5) | I6: =SUMIFS('Payroll'!$E$6:$E$35,'Payroll'!$D$6:$D$35,I$5) | J6: =SUMIFS('Payroll'!$E$6:$E$35,'Payroll'!$D$6:$D$35,J$5) | K6: =SUMIFS('Payroll'!$E$6:$E$35,'Payroll'!$D$6:$D$35,K$5) | L6: =SUMIFS('Payroll'!$E$6:$E$35,'Payroll'!$D$6:$D$35,L$5) | M6: =SUMIFS('Payroll'!$E$6:$E$35,'Payroll'!$D$6:$D$35,M$5) | ... Q6: =SUMIFS('Payroll'!$E$6:$E$35,'Payroll'!$D$6:$D$35,Q$5) | R6: =IF(COUNT(F6:Q6)=0,"",SUM(F6:Q6))
B7: Studio Lease | C7: Rent & Facilities | D7: Fixed | E7: 1 | F7: 2400 | G7: 2400 | H7: 2400 | I7: 2400 | J7: 2400 | K7: 2400 | L7: 2400 | M7: 2400 | N7: 2400 | O7: 2400 | P7: 2400 | Q7: 2400 | R7: =IF(COUNT(F7:Q7)=0,"",SUM(F7:Q7))
B8: Software & SaaS | C8: Software & Subscriptions | D8: Fixed | E8: 5 | F8: 640 | G8: 640 | H8: 640 | I8: 640 | J8: 640 | K8: 640 | L8: 640 | M8: 640 | N8: 640 | O8: 640 | P8: 640 | Q8: 640 | R8: =IF(COUNT(F8:Q8)=0,"",SUM(F8:Q8))
B9: Business Insurance | C9: Insurance | D9: Fixed | F9: 1800 | I9: 1800 | L9: 1800 | O9: 1800 | R9: =IF(COUNT(F9:Q9)=0,"",SUM(F9:Q9))
B10: Bookkeeping | C10: Professional Fees | D10: Fixed | E10: 10 | F10: 450 | G10: 450 | H10: 450 | I10: 450 | J10: 450 | K10: 450 | L10: 450 | M10: 450 | N10: 450 | O10: 450 | P10: 450 | Q10: 450 | R10: =IF(COUNT(F10:Q10)=0,"",SUM(F10:Q10))
B11: Ads & Promotion | C11: Marketing & Advertising | D11: Variable | F11: 900 | G11: 900 | H11: 900 | I11: 900 | J11: 900 | K11: 900 | L11: 900 | M11: 900 | N11: 900 | O11: 900 | P11: 900 | Q11: 900 | R11: =IF(COUNT(F11:Q11)=0,"",SUM(F11:Q11))
B12: Freelance Contractors | C12: Contractors | D12: Variable | F12: 1500 | G12: 1200 | H12: 2500 | I12: 2000 | J12: 1800 | K12: 3500 | L12: 1500 | M12: 1200 | N12: 2500 | O12: 3000 | P12: 4000 | Q12: 2000 | R12: =IF(COUNT(F12:Q12)=0,"",SUM(F12:Q12))
B13: Merchant Fees | C13: Bank & Merchant Fees | D13: Variable | F13: 320 | G13: 320 | H13: 320 | I13: 320 | J13: 320 | K13: 320 | L13: 320 | M13: 320 | N13: 320 | O13: 320 | P13: 320 | Q13: 320 | R13: =IF(COUNT(F13:Q13)=0,"",SUM(F13:Q13))
B14: Equipment Upgrade | C14: Equipment | D14: Variable | H14: 4200 | R14: =IF(COUNT(F14:Q14)=0,"",SUM(F14:Q14))
B15: Estimated Taxes | C15: Taxes & Licenses | D15: Fixed | F15: 4500 | I15: 4500 | L15: 4500 | O15: 4500 | R15: =IF(COUNT(F15:Q15)=0,"",SUM(F15:Q15))
R16: =IF(COUNT(F16:Q16)=0,"",SUM(F16:Q16))
R17: =IF(COUNT(F17:Q17)=0,"",SUM(F17:Q17))
R18: =IF(COUNT(F18:Q18)=0,"",SUM(F18:Q18))
R19: =IF(COUNT(F19:Q19)=0,"",SUM(F19:Q19))
R20: =IF(COUNT(F20:Q20)=0,"",SUM(F20:Q20))
R21: =IF(COUNT(F21:Q21)=0,"",SUM(F21:Q21))
R22: =IF(COUNT(F22:Q22)=0,"",SUM(F22:Q22))
R23: =IF(COUNT(F23:Q23)=0,"",SUM(F23:Q23))
R24: =IF(COUNT(F24:Q24)=0,"",SUM(F24:Q24))
R25: =IF(COUNT(F25:Q25)=0,"",SUM(F25:Q25))
R26: =IF(COUNT(F26:Q26)=0,"",SUM(F26:Q26))
R27: =IF(COUNT(F27:Q27)=0,"",SUM(F27:Q27))
... R66: =IF(COUNT(F66:Q66)=0,"",SUM(F66:Q66))
B67: TOTAL | F67: =SUM(F6:F66) | G67: =SUM(G6:G66) | H67: =SUM(H6:H66) | I67: =SUM(I6:I66) | J67: =SUM(J6:J66) | K67: =SUM(K6:K66) | L67: =SUM(L6:L66) | M67: =SUM(M6:M66) | ... R67: =SUM(R6:R66)

Sheet Reserve Goals
B2: Reserve Goals
B3: Cash reserves, tax set-asides and equipment funds. Progress and monthly amount needed update automatically.
B5: Goal | C5: Target | D5: Saved So Far | E5: Remaining | F5: Progress | G5: Target Date | H5: Months Left | I5: Needed / Month
B6: Cash Reserve (3 months) | C6: 45000 | D6: 18000 | E6: =IF(C6="","",MAX(0,C6-D6)) | F6: =IF(C6="","",IFERROR(MIN(1,D6/C6),0)) | G6: 46387 | H6: =IF(G6="","",IFERROR(MAX(0,DATEDIF(TODAY(),G6,"m")),0)) | I6: =IF(OR(E6="",H6=""),"",E6/MAX(1,H6))
B7: Tax Set-Aside | C7: 18000 | D7: 4500 | E7: =IF(C7="","",MAX(0,C7-D7)) | F7: =IF(C7="","",IFERROR(MIN(1,D7/C7),0)) | G7: 46492 | H7: =IF(G7="","",IFERROR(MAX(0,DATEDIF(TODAY(),G7,"m")),0)) | I7: =IF(OR(E7="",H7=""),"",E7/MAX(1,H7))
E8: =IF(C8="","",MAX(0,C8-D8)) | F8: =IF(C8="","",IFERROR(MIN(1,D8/C8),0)) | H8: =IF(G8="","",IFERROR(MAX(0,DATEDIF(TODAY(),G8,"m")),0)) | I8: =IF(OR(E8="",H8=""),"",E8/MAX(1,H8))
E9: =IF(C9="","",MAX(0,C9-D9)) | F9: =IF(C9="","",IFERROR(MIN(1,D9/C9),0)) | H9: =IF(G9="","",IFERROR(MAX(0,DATEDIF(TODAY(),G9,"m")),0)) | I9: =IF(OR(E9="",H9=""),"",E9/MAX(1,H9))
E10: =IF(C10="","",MAX(0,C10-D10)) | F10: =IF(C10="","",IFERROR(MIN(1,D10/C10),0)) | H10: =IF(G10="","",IFERROR(MAX(0,DATEDIF(TODAY(),G10,"m")),0)) | I10: =IF(OR(E10="",H10=""),"",E10/MAX(1,H10))
E11: =IF(C11="","",MAX(0,C11-D11)) | F11: =IF(C11="","",IFERROR(MIN(1,D11/C11),0)) | H11: =IF(G11="","",IFERROR(MAX(0,DATEDIF(TODAY(),G11,"m")),0)) | I11: =IF(OR(E11="",H11=""),"",E11/MAX(1,H11))
E12: =IF(C12="","",MAX(0,C12-D12)) | F12: =IF(C12="","",IFERROR(MIN(1,D12/C12),0)) | H12: =IF(G12="","",IFERROR(MAX(0,DATEDIF(TODAY(),G12,"m")),0)) | I12: =IF(OR(E12="",H12=""),"",E12/MAX(1,H12))
E13: =IF(C13="","",MAX(0,C13-D13)) | F13: =IF(C13="","",IFERROR(MIN(1,D13/C13),0)) | H13: =IF(G13="","",IFERROR(MAX(0,DATEDIF(TODAY(),G13,"m")),0)) | I13: =IF(OR(E13="",H13=""),"",E13/MAX(1,H13))
E14: =IF(C14="","",MAX(0,C14-D14)) | F14: =IF(C14="","",IFERROR(MIN(1,D14/C14),0)) | H14: =IF(G14="","",IFERROR(MAX(0,DATEDIF(TODAY(),G14,"m")),0)) | I14: =IF(OR(E14="",H14=""),"",E14/MAX(1,H14))
E15: =IF(C15="","",MAX(0,C15-D15)) | F15: =IF(C15="","",IFERROR(MIN(1,D15/C15),0)) | H15: =IF(G15="","",IFERROR(MAX(0,DATEDIF(TODAY(),G15,"m")),0)) | I15: =IF(OR(E15="",H15=""),"",E15/MAX(1,H15))
B16: TOTAL | C16: =SUM(C6:C15) | D16: =SUM(D6:D15) | E16: =SUM(E6:E15) | F16: =IFERROR(D16/C16,0)

Sheet Loans & Credit
B2: Loans & Credit
B3: Payoff time assumes the minimum payment every month with no new draws.
B5: Loan / Credit Line | C5: Balance | D5: APR % | E5: Min Payment | F5: Months to Payoff | G5: Est. Interest | H5: Payoff Date
B6: Business Credit Card | C6: 6400 | D6: 19.9 | E6: 220 | F6: =IF(OR(C6="",E6=""),"",IF(N(D6)=0,ROUNDUP(C6/E6,0),IFERROR(ROUNDUP(NPER(D6/1200,-E6,C6),0),"Never"))) | G6: =IF(ISNUMBER(F6),MAX(0,F6*E6-C6),"") | H6: =IF(ISNUMBER(F6),EDATE(TODAY(),F6),"")
B7: Equipment Loan | C7: 21000 | D7: 7.25 | E7: 640 | F7: =IF(OR(C7="",E7=""),"",IF(N(D7)=0,ROUNDUP(C7/E7,0),IFERROR(ROUNDUP(NPER(D7/1200,-E7,C7),0),"Never"))) | G7: =IF(ISNUMBER(F7),MAX(0,F7*E7-C7),"") | H7: =IF(ISNUMBER(F7),EDATE(TODAY(),F7),"")
F8: =IF(OR(C8="",E8=""),"",IF(N(D8)=0,ROUNDUP(C8/E8,0),IFERROR(ROUNDUP(NPER(D8/1200,-E8,C8),0),"Never"))) | G8: =IF(ISNUMBER(F8),MAX(0,F8*E8-C8),"") | H8: =IF(ISNUMBER(F8),EDATE(TODAY(),F8),"")
F9: =IF(OR(C9="",E9=""),"",IF(N(D9)=0,ROUNDUP(C9/E9,0),IFERROR(ROUNDUP(NPER(D9/1200,-E9,C9),0),"Never"))) | G9: =IF(ISNUMBER(F9),MAX(0,F9*E9-C9),"") | H9: =IF(ISNUMBER(F9),EDATE(TODAY(),F9),"")
F10: =IF(OR(C10="",E10=""),"",IF(N(D10)=0,ROUNDUP(C10/E10,0),IFERROR(ROUNDUP(NPER(D10/1200,-E10,C10),0),"Never"))) | G10: =IF(ISNUMBER(F10),MAX(0,F10*E10-C10),"") | H10: =IF(ISNUMBER(F10),EDATE(TODAY(),F10),"")
F11: =IF(OR(C11="",E11=""),"",IF(N(D11)=0,ROUNDUP(C11/E11,0),IFERROR(ROUNDUP(NPER(D11/1200,-E11,C11),0),"Never"))) | G11: =IF(ISNUMBER(F11),MAX(0,F11*E11-C11),"") | H11: =IF(ISNUMBER(F11),EDATE(TODAY(),F11),"")
F12: =IF(OR(C12="",E12=""),"",IF(N(D12)=0,ROUNDUP(C12/E12,0),IFERROR(ROUNDUP(NPER(D12/1200,-E12,C12),0),"Never"))) | G12: =IF(ISNUMBER(F12),MAX(0,F12*E12-C12),"") | H12: =IF(ISNUMBER(F12),EDATE(TODAY(),F12),"")
F13: =IF(OR(C13="",E13=""),"",IF(N(D13)=0,ROUNDUP(C13/E13,0),IFERROR(ROUNDUP(NPER(D13/1200,-E13,C13),0),"Never"))) | G13: =IF(ISNUMBER(F13),MAX(0,F13*E13-C13),"") | H13: =IF(ISNUMBER(F13),EDATE(TODAY(),F13),"")
F14: =IF(OR(C14="",E14=""),"",IF(N(D14)=0,ROUNDUP(C14/E14,0),IFERROR(ROUNDUP(NPER(D14/1200,-E14,C14),0),"Never"))) | G14: =IF(ISNUMBER(F14),MAX(0,F14*E14-C14),"") | H14: =IF(ISNUMBER(F14),EDATE(TODAY(),F14),"")
F15: =IF(OR(C15="",E15=""),"",IF(N(D15)=0,ROUNDUP(C15/E15,0),IFERROR(ROUNDUP(NPER(D15/1200,-E15,C15),0),"Never"))) | G15: =IF(ISNUMBER(F15),MAX(0,F15*E15-C15),"") | H15: =IF(ISNUMBER(F15),EDATE(TODAY(),F15),"")
B16: TOTAL | C16: =SUM(C6:C15) | E16: =SUM(E6:E15)

Sheet Lists
A1: Expense Categories | B1: Types | C1: Income Categories
A2: Payroll | B2: Fixed | C2: Product Sales
A3: Rent & Facilities | B3: Variable | C3: Services
A4: Utilities | C4: Recurring / Subscriptions
A5: Software & Subscriptions | C5: Consulting
A6: Marketing & Advertising | C6: Grants
A7: Inventory / COGS | C7: Interest
A8: Contractors | C8: Other
A9: Supplies
A10: Insurance
A11: Professional Fees
A12: Travel & Meals
A13: Equipment
A14: Taxes & Licenses
A15: Bank & Merchant Fees
A16: Loan Payments
A17: Owner Pay
A18: Other
