Workbook

Sheet Dashboard
B2: 2026 Budget Planner
B3: Annual Overview | Jan 2026 - Dec 2026 | Paid Bi-weekly | Alex Rivera
B5: MONEY IN | D5: MONEY OUT | F5: NET SAVINGS | H5: SAVINGS RATE | K5: AVG MONTHLY SPEND | M5: PAYCHECKS
B6: =D42 | D6: =G42 | F6: =H42 | H6: =IFERROR(H42/D42,0) | K6: =G42/12 | M6: =C42
B7: earned this year | D7: bills + expenses | F7: money in - money out | H7: of income kept | K7: money out / 12 | M7: paydays this year
B28: Monthly Breakdown | K28: Spending by Category
B29: Month | C29: Paychecks | D29: Money In | E29: Bills | F29: Expenses | G29: Money Out | H29: Net | I29: Savings Rate | K29: Category | L29: Annual | M29: Monthly Avg | N29: % of Spend
B30: 46023 | C30: =COUNTIFS('Paychecks'!$D$6:$D$37,B30) | D30: ='Income'!D22 | E30: =SUMIFS('Expenses'!$F$6:$F$65,'Expenses'!$D$6:$D$65,"Bill") | F30: =SUMIFS('Expenses'!$F$6:$F$65,'Expenses'!$D$6:$D$65,"Expense") | G30: =E30+F30 | H30: =D30-G30 | I30: =IFERROR(H30/D30,0) | K30: Housing | L30: =SUMIF('Expenses'!$C$6:$C$65,K30,'Expenses'!$R$6:$R$65) | M30: =L30/12 | N30: =IFERROR(L30/$L$43,0)
B31: 46054 | C31: =COUNTIFS('Paychecks'!$D$6:$D$37,B31) | D31: ='Income'!E22 | E31: =SUMIFS('Expenses'!$G$6:$G$65,'Expenses'!$D$6:$D$65,"Bill") | F31: =SUMIFS('Expenses'!$G$6:$G$65,'Expenses'!$D$6:$D$65,"Expense") | G31: =E31+F31 | H31: =D31-G31 | I31: =IFERROR(H31/D31,0) | K31: Utilities | L31: =SUMIF('Expenses'!$C$6:$C$65,K31,'Expenses'!$R$6:$R$65) | M31: =L31/12 | N31: =IFERROR(L31/$L$43,0)
B32: 46082 | C32: =COUNTIFS('Paychecks'!$D$6:$D$37,B32) | D32: ='Income'!F22 | E32: =SUMIFS('Expenses'!$H$6:$H$65,'Expenses'!$D$6:$D$65,"Bill") | F32: =SUMIFS('Expenses'!$H$6:$H$65,'Expenses'!$D$6:$D$65,"Expense") | G32: =E32+F32 | H32: =D32-G32 | I32: =IFERROR(H32/D32,0) | K32: Transportation | L32: =SUMIF('Expenses'!$C$6:$C$65,K32,'Expenses'!$R$6:$R$65) | M32: =L32/12 | N32: =IFERROR(L32/$L$43,0)
B33: 46113 | C33: =COUNTIFS('Paychecks'!$D$6:$D$37,B33) | D33: ='Income'!G22 | E33: =SUMIFS('Expenses'!$I$6:$I$65,'Expenses'!$D$6:$D$65,"Bill") | F33: =SUMIFS('Expenses'!$I$6:$I$65,'Expenses'!$D$6:$D$65,"Expense") | G33: =E33+F33 | H33: =D33-G33 | I33: =IFERROR(H33/D33,0) | K33: Food | L33: =SUMIF('Expenses'!$C$6:$C$65,K33,'Expenses'!$R$6:$R$65) | M33: =L33/12 | N33: =IFERROR(L33/$L$43,0)
B34: 46143 | C34: =COUNTIFS('Paychecks'!$D$6:$D$37,B34) | D34: ='Income'!H22 | E34: =SUMIFS('Expenses'!$J$6:$J$65,'Expenses'!$D$6:$D$65,"Bill") | F34: =SUMIFS('Expenses'!$J$6:$J$65,'Expenses'!$D$6:$D$65,"Expense") | G34: =E34+F34 | H34: =D34-G34 | I34: =IFERROR(H34/D34,0) | K34: Insurance | L34: =SUMIF('Expenses'!$C$6:$C$65,K34,'Expenses'!$R$6:$R$65) | M34: =L34/12 | N34: =IFERROR(L34/$L$43,0)
B35: 46174 | C35: =COUNTIFS('Paychecks'!$D$6:$D$37,B35) | D35: ='Income'!I22 | E35: =SUMIFS('Expenses'!$K$6:$K$65,'Expenses'!$D$6:$D$65,"Bill") | F35: =SUMIFS('Expenses'!$K$6:$K$65,'Expenses'!$D$6:$D$65,"Expense") | G35: =E35+F35 | H35: =D35-G35 | I35: =IFERROR(H35/D35,0) | K35: Health | L35: =SUMIF('Expenses'!$C$6:$C$65,K35,'Expenses'!$R$6:$R$65) | M35: =L35/12 | N35: =IFERROR(L35/$L$43,0)
B36: 46204 | C36: =COUNTIFS('Paychecks'!$D$6:$D$37,B36) | D36: ='Income'!J22 | E36: =SUMIFS('Expenses'!$L$6:$L$65,'Expenses'!$D$6:$D$65,"Bill") | F36: =SUMIFS('Expenses'!$L$6:$L$65,'Expenses'!$D$6:$D$65,"Expense") | G36: =E36+F36 | H36: =D36-G36 | I36: =IFERROR(H36/D36,0) | K36: Debt Payments | L36: =SUMIF('Expenses'!$C$6:$C$65,K36,'Expenses'!$R$6:$R$65) | M36: =L36/12 | N36: =IFERROR(L36/$L$43,0)
B37: 46235 | C37: =COUNTIFS('Paychecks'!$D$6:$D$37,B37) | D37: ='Income'!K22 | E37: =SUMIFS('Expenses'!$M$6:$M$65,'Expenses'!$D$6:$D$65,"Bill") | F37: =SUMIFS('Expenses'!$M$6:$M$65,'Expenses'!$D$6:$D$65,"Expense") | G37: =E37+F37 | H37: =D37-G37 | I37: =IFERROR(H37/D37,0) | K37: Subscriptions | L37: =SUMIF('Expenses'!$C$6:$C$65,K37,'Expenses'!$R$6:$R$65) | M37: =L37/12 | N37: =IFERROR(L37/$L$43,0)
B38: 46266 | C38: =COUNTIFS('Paychecks'!$D$6:$D$37,B38) | D38: ='Income'!L22 | E38: =SUMIFS('Expenses'!$N$6:$N$65,'Expenses'!$D$6:$D$65,"Bill") | F38: =SUMIFS('Expenses'!$N$6:$N$65,'Expenses'!$D$6:$D$65,"Expense") | G38: =E38+F38 | H38: =D38-G38 | I38: =IFERROR(H38/D38,0) | K38: Entertainment | L38: =SUMIF('Expenses'!$C$6:$C$65,K38,'Expenses'!$R$6:$R$65) | M38: =L38/12 | N38: =IFERROR(L38/$L$43,0)
B39: 46296 | C39: =COUNTIFS('Paychecks'!$D$6:$D$37,B39) | D39: ='Income'!M22 | E39: =SUMIFS('Expenses'!$O$6:$O$65,'Expenses'!$D$6:$D$65,"Bill") | F39: =SUMIFS('Expenses'!$O$6:$O$65,'Expenses'!$D$6:$D$65,"Expense") | G39: =E39+F39 | H39: =D39-G39 | I39: =IFERROR(H39/D39,0) | K39: Personal | L39: =SUMIF('Expenses'!$C$6:$C$65,K39,'Expenses'!$R$6:$R$65) | M39: =L39/12 | N39: =IFERROR(L39/$L$43,0)
B40: 46327 | C40: =COUNTIFS('Paychecks'!$D$6:$D$37,B40) | D40: ='Income'!N22 | E40: =SUMIFS('Expenses'!$P$6:$P$65,'Expenses'!$D$6:$D$65,"Bill") | F40: =SUMIFS('Expenses'!$P$6:$P$65,'Expenses'!$D$6:$D$65,"Expense") | G40: =E40+F40 | H40: =D40-G40 | I40: =IFERROR(H40/D40,0) | K40: Savings | L40: =SUMIF('Expenses'!$C$6:$C$65,K40,'Expenses'!$R$6:$R$65) | M40: =L40/12 | N40: =IFERROR(L40/$L$43,0)
B41: 46357 | C41: =COUNTIFS('Paychecks'!$D$6:$D$37,B41) | D41: ='Income'!O22 | E41: =SUMIFS('Expenses'!$Q$6:$Q$65,'Expenses'!$D$6:$D$65,"Bill") | F41: =SUMIFS('Expenses'!$Q$6:$Q$65,'Expenses'!$D$6:$D$65,"Expense") | G41: =E41+F41 | H41: =D41-G41 | I41: =IFERROR(H41/D41,0) | K41: Giving | L41: =SUMIF('Expenses'!$C$6:$C$65,K41,'Expenses'!$R$6:$R$65) | M41: =L41/12 | N41: =IFERROR(L41/$L$43,0)
B42: TOTAL | C42: =SUM(C30:C41) | D42: =SUM(D30:D41) | E42: =SUM(E30:E41) | F42: =SUM(F30:F41) | G42: =SUM(G30:G41) | H42: =SUM(H30:H41) | I42: =IFERROR(H42/D42,0) | K42: Other | L42: =SUMIF('Expenses'!$C$6:$C$65,K42,'Expenses'!$R$6:$R$65) | M42: =L42/12 | N42: =IFERROR(L42/$L$43,0)
K43: TOTAL | L43: =SUM(L30:L42) | M43: =SUM(M30:M42) | N43: =IF(L43>0,1,0)
B46: Savings Goals | H46: Debt Tracker
B47: TOTAL TARGET | D47: SAVED SO FAR | F47: PROGRESS | H47: TOTAL DEBT | K47: MIN PAYMENTS
B48: ='Savings Goals'!C16 | D48: ='Savings Goals'!D16 | F48: =IFERROR('Savings Goals'!D16/'Savings Goals'!C16,0) | H48: ='Debt Tracker'!C16 | K48: ='Debt Tracker'!E16
B49: across all goals | D49: toward your goals | F49: of total target | H49: current balances | K49: per month

Sheet Income
B2: Income
B3: Type amounts in the input cells. Your paycheck row fills automatically from the Paychecks sheet.
B5: Source | C5: Category | D5: 46023 | E5: 46054 | F5: 46082 | G5: 46113 | H5: 46143 | I5: 46174 | J5: 46204 | K5: 46235 | L5: 46266 | M5: 46296 | N5: 46327 | O5: 46357 | P5: Annual Total
B6: Paycheck (Bi-weekly) | C6: Primary | D6: =SUMIFS('Paychecks'!$E$6:$E$37,'Paychecks'!$D$6:$D$37,D$5) | E6: =SUMIFS('Paychecks'!$E$6:$E$37,'Paychecks'!$D$6:$D$37,E$5) | F6: =SUMIFS('Paychecks'!$E$6:$E$37,'Paychecks'!$D$6:$D$37,F$5) | G6: =SUMIFS('Paychecks'!$E$6:$E$37,'Paychecks'!$D$6:$D$37,G$5) | H6: =SUMIFS('Paychecks'!$E$6:$E$37,'Paychecks'!$D$6:$D$37,H$5) | I6: =SUMIFS('Paychecks'!$E$6:$E$37,'Paychecks'!$D$6:$D$37,I$5) | J6: =SUMIFS('Paychecks'!$E$6:$E$37,'Paychecks'!$D$6:$D$37,J$5) | K6: =SUMIFS('Paychecks'!$E$6:$E$37,'Paychecks'!$D$6:$D$37,K$5) | ... O6: =SUMIFS('Paychecks'!$E$6:$E$37,'Paychecks'!$D$6:$D$37,O$5) | P6: =IF(COUNT(D6:O6)=0,"",SUM(D6:O6))
B7: Freelance design | C7: Side Income | D7: 400 | E7: 400 | F7: 400 | G7: 400 | H7: 400 | I7: 400 | J7: 400 | K7: 400 | L7: 400 | M7: 400 | N7: 400 | O7: 400 | P7: =IF(COUNT(D7:O7)=0,"",SUM(D7:O7))
B8: Tax refund | C8: Refunds | G8: 1200 | P8: =IF(COUNT(D8:O8)=0,"",SUM(D8:O8))
P9: =IF(COUNT(D9:O9)=0,"",SUM(D9:O9))
P10: =IF(COUNT(D10:O10)=0,"",SUM(D10:O10))
P11: =IF(COUNT(D11:O11)=0,"",SUM(D11:O11))
P12: =IF(COUNT(D12:O12)=0,"",SUM(D12:O12))
P13: =IF(COUNT(D13:O13)=0,"",SUM(D13:O13))
P14: =IF(COUNT(D14:O14)=0,"",SUM(D14:O14))
P15: =IF(COUNT(D15:O15)=0,"",SUM(D15:O15))
P16: =IF(COUNT(D16:O16)=0,"",SUM(D16:O16))
P17: =IF(COUNT(D17:O17)=0,"",SUM(D17:O17))
P18: =IF(COUNT(D18:O18)=0,"",SUM(D18:O18))
P19: =IF(COUNT(D19:O19)=0,"",SUM(D19:O19))
P20: =IF(COUNT(D20:O20)=0,"",SUM(D20:O20))
P21: =IF(COUNT(D21:O21)=0,"",SUM(D21:O21))
B22: TOTAL INCOME | D22: =SUM(D6:D21) | E22: =SUM(E6:E21) | F22: =SUM(F6:F21) | G22: =SUM(G6:G21) | H22: =SUM(H6:H21) | I22: =SUM(I6:I21) | J22: =SUM(J6:J21) | K22: =SUM(K6:K21) | ... P22: =SUM(P6:P21)

Sheet Paychecks
B2: Paycheck Calendar
B3: Every payday in your budget period. Edit Net Pay for any paycheck that differs (bonus, overtime, unpaid leave).
B5: # | C5: Pay Date | D5: Month | E5: Net Pay | F5: Notes
B6: 1 | C6: 46031 | D6: =IF(C6="","",DATE(YEAR(C6),MONTH(C6),1)) | E6: 2150
B7: 2 | C7: 46045 | D7: =IF(C7="","",DATE(YEAR(C7),MONTH(C7),1)) | E7: 2150
B8: 3 | C8: 46059 | D8: =IF(C8="","",DATE(YEAR(C8),MONTH(C8),1)) | E8: 2150
B9: 4 | C9: 46073 | D9: =IF(C9="","",DATE(YEAR(C9),MONTH(C9),1)) | E9: 2150
B10: 5 | C10: 46087 | D10: =IF(C10="","",DATE(YEAR(C10),MONTH(C10),1)) | E10: 2150
B11: 6 | C11: 46101 | D11: =IF(C11="","",DATE(YEAR(C11),MONTH(C11),1)) | E11: 2150
B12: 7 | C12: 46115 | D12: =IF(C12="","",DATE(YEAR(C12),MONTH(C12),1)) | E12: 2150
B13: 8 | C13: 46129 | D13: =IF(C13="","",DATE(YEAR(C13),MONTH(C13),1)) | E13: 2150
B14: 9 | C14: 46143 | D14: =IF(C14="","",DATE(YEAR(C14),MONTH(C14),1)) | E14: 2150
B15: 10 | C15: 46157 | D15: =IF(C15="","",DATE(YEAR(C15),MONTH(C15),1)) | E15: 2150
B16: 11 | C16: 46171 | D16: =IF(C16="","",DATE(YEAR(C16),MONTH(C16),1)) | E16: 2150
B17: 12 | C17: 46185 | D17: =IF(C17="","",DATE(YEAR(C17),MONTH(C17),1)) | E17: 2150
... B31: 26 | C31: 46381 | D31: =IF(C31="","",DATE(YEAR(C31),MONTH(C31),1)) | E31: 2150
D32: =IF(C32="","",DATE(YEAR(C32),MONTH(C32),1))
D33: =IF(C33="","",DATE(YEAR(C33),MONTH(C33),1))
D34: =IF(C34="","",DATE(YEAR(C34),MONTH(C34),1))
D35: =IF(C35="","",DATE(YEAR(C35),MONTH(C35),1))
D36: =IF(C36="","",DATE(YEAR(C36),MONTH(C36),1))
D37: =IF(C37="","",DATE(YEAR(C37),MONTH(C37),1))
B38: TOTAL | E38: =SUM(E6:E37)

Sheet Expenses
B2: Bills & Expenses
B3: Bills = fixed recurring payments. Expenses = variable spending. Pick Category and Type from the dropdowns.
B5: Name | C5: Category | D5: Type | E5: Due Day | F5: 46023 | G5: 46054 | H5: 46082 | I5: 46113 | J5: 46143 | K5: 46174 | L5: 46204 | M5: 46235 | N5: 46266 | O5: 46296 | P5: 46327 | Q5: 46357 | R5: Annual Total
B6: Rent | C6: Housing | D6: Bill | E6: 1 | F6: 1650 | G6: 1650 | H6: 1650 | I6: 1650 | J6: 1650 | K6: 1650 | L6: 1650 | M6: 1650 | N6: 1650 | O6: 1650 | P6: 1650 | Q6: 1650 | R6: =IF(COUNT(F6:Q6)=0,"",SUM(F6:Q6))
B7: Electricity | C7: Utilities | D7: Bill | E7: 12 | F7: 110 | G7: 110 | H7: 110 | I7: 110 | J7: 110 | K7: 110 | L7: 110 | M7: 110 | N7: 110 | O7: 110 | P7: 110 | Q7: 110 | R7: =IF(COUNT(F7:Q7)=0,"",SUM(F7:Q7))
B8: Internet | C8: Utilities | D8: Bill | E8: 18 | F8: 70 | G8: 70 | H8: 70 | I8: 70 | J8: 70 | K8: 70 | L8: 70 | M8: 70 | N8: 70 | O8: 70 | P8: 70 | Q8: 70 | R8: =IF(COUNT(F8:Q8)=0,"",SUM(F8:Q8))
B9: Phone | C9: Utilities | D9: Bill | E9: 22 | F9: 85 | G9: 85 | H9: 85 | I9: 85 | J9: 85 | K9: 85 | L9: 85 | M9: 85 | N9: 85 | O9: 85 | P9: 85 | Q9: 85 | R9: =IF(COUNT(F9:Q9)=0,"",SUM(F9:Q9))
B10: Car Payment | C10: Transportation | D10: Bill | E10: 5 | F10: 385 | G10: 385 | H10: 385 | I10: 385 | J10: 385 | K10: 385 | L10: 385 | M10: 385 | N10: 385 | O10: 385 | P10: 385 | Q10: 385 | R10: =IF(COUNT(F10:Q10)=0,"",SUM(F10:Q10))
B11: Car Insurance | C11: Insurance | D11: Bill | F11: 720 | I11: 720 | L11: 720 | O11: 720 | R11: =IF(COUNT(F11:Q11)=0,"",SUM(F11:Q11))
B12: Gas / Fuel | C12: Transportation | D12: Expense | F12: 195 | G12: 195 | H12: 195 | I12: 195 | J12: 195 | K12: 195 | L12: 195 | M12: 195 | N12: 195 | O12: 195 | P12: 195 | Q12: 195 | R12: =IF(COUNT(F12:Q12)=0,"",SUM(F12:Q12))
B13: Groceries | C13: Food | D13: Expense | F13: 520 | G13: 520 | H13: 520 | I13: 520 | J13: 520 | K13: 520 | L13: 520 | M13: 520 | N13: 520 | O13: 520 | P13: 520 | Q13: 520 | R13: =IF(COUNT(F13:Q13)=0,"",SUM(F13:Q13))
B14: Dining Out | C14: Food | D14: Expense | F14: 180 | G14: 180 | H14: 180 | I14: 180 | J14: 180 | K14: 180 | L14: 180 | M14: 180 | N14: 180 | O14: 180 | P14: 180 | Q14: 180 | R14: =IF(COUNT(F14:Q14)=0,"",SUM(F14:Q14))
B15: Streaming Services | C15: Subscriptions | D15: Bill | E15: 3 | F15: 38 | G15: 38 | H15: 38 | I15: 38 | J15: 38 | K15: 38 | L15: 38 | M15: 38 | N15: 38 | O15: 38 | P15: 38 | Q15: 38 | R15: =IF(COUNT(F15:Q15)=0,"",SUM(F15:Q15))
B16: Gym | C16: Health | D16: Bill | E16: 1 | F16: 45 | G16: 45 | H16: 45 | I16: 45 | J16: 45 | K16: 45 | L16: 45 | M16: 45 | N16: 45 | O16: 45 | P16: 45 | Q16: 45 | R16: =IF(COUNT(F16:Q16)=0,"",SUM(F16:Q16))
B17: Holiday Gifts | C17: Giving | D17: Expense | Q17: 600 | R17: =IF(COUNT(F17:Q17)=0,"",SUM(F17:Q17))
B18: Emergency Fund Transfer | C18: Savings | D18: Bill | E18: 15 | F18: 300 | G18: 300 | H18: 300 | I18: 300 | J18: 300 | K18: 300 | L18: 300 | M18: 300 | N18: 300 | O18: 300 | P18: 300 | Q18: 300 | R18: =IF(COUNT(F18:Q18)=0,"",SUM(F18:Q18))
R19: =IF(COUNT(F19:Q19)=0,"",SUM(F19:Q19))
R20: =IF(COUNT(F20:Q20)=0,"",SUM(F20:Q20))
R21: =IF(COUNT(F21:Q21)=0,"",SUM(F21:Q21))
R22: =IF(COUNT(F22:Q22)=0,"",SUM(F22:Q22))
R23: =IF(COUNT(F23:Q23)=0,"",SUM(F23:Q23))
R24: =IF(COUNT(F24:Q24)=0,"",SUM(F24:Q24))
R25: =IF(COUNT(F25:Q25)=0,"",SUM(F25:Q25))
R26: =IF(COUNT(F26:Q26)=0,"",SUM(F26:Q26))
R27: =IF(COUNT(F27:Q27)=0,"",SUM(F27:Q27))
R28: =IF(COUNT(F28:Q28)=0,"",SUM(F28:Q28))
R29: =IF(COUNT(F29:Q29)=0,"",SUM(F29:Q29))
R30: =IF(COUNT(F30:Q30)=0,"",SUM(F30:Q30))
... R65: =IF(COUNT(F65:Q65)=0,"",SUM(F65:Q65))
B66: TOTAL | F66: =SUM(F6:F65) | G66: =SUM(G6:G65) | H66: =SUM(H6:H65) | I66: =SUM(I6:I65) | J66: =SUM(J6:J65) | K66: =SUM(K6:K65) | L66: =SUM(L6:L65) | M66: =SUM(M6:M65) | ... R66: =SUM(R6:R65)

Sheet Savings Goals
B2: Savings Goals
B3: Track each goal. Remaining, progress and monthly amount needed update automatically.
B5: Goal | C5: Target | D5: Saved So Far | E5: Remaining | F5: Progress | G5: Target Date | H5: Months Left | I5: Needed / Month
B6: Emergency Fund | C6: 10000 | D6: 3200 | E6: =IF(C6="","",MAX(0,C6-D6)) | F6: =IF(C6="","",IFERROR(MIN(1,D6/C6),0)) | G6: 46387 | H6: =IF(G6="","",IFERROR(MAX(0,DATEDIF(TODAY(),G6,"m")),0)) | I6: =IF(OR(E6="",H6=""),"",E6/MAX(1,H6))
B7: Japan Trip | C7: 4500 | D7: 900 | E7: =IF(C7="","",MAX(0,C7-D7)) | F7: =IF(C7="","",IFERROR(MIN(1,D7/C7),0)) | G7: 46478 | H7: =IF(G7="","",IFERROR(MAX(0,DATEDIF(TODAY(),G7,"m")),0)) | I7: =IF(OR(E7="",H7=""),"",E7/MAX(1,H7))
E8: =IF(C8="","",MAX(0,C8-D8)) | F8: =IF(C8="","",IFERROR(MIN(1,D8/C8),0)) | H8: =IF(G8="","",IFERROR(MAX(0,DATEDIF(TODAY(),G8,"m")),0)) | I8: =IF(OR(E8="",H8=""),"",E8/MAX(1,H8))
E9: =IF(C9="","",MAX(0,C9-D9)) | F9: =IF(C9="","",IFERROR(MIN(1,D9/C9),0)) | H9: =IF(G9="","",IFERROR(MAX(0,DATEDIF(TODAY(),G9,"m")),0)) | I9: =IF(OR(E9="",H9=""),"",E9/MAX(1,H9))
E10: =IF(C10="","",MAX(0,C10-D10)) | F10: =IF(C10="","",IFERROR(MIN(1,D10/C10),0)) | H10: =IF(G10="","",IFERROR(MAX(0,DATEDIF(TODAY(),G10,"m")),0)) | I10: =IF(OR(E10="",H10=""),"",E10/MAX(1,H10))
E11: =IF(C11="","",MAX(0,C11-D11)) | F11: =IF(C11="","",IFERROR(MIN(1,D11/C11),0)) | H11: =IF(G11="","",IFERROR(MAX(0,DATEDIF(TODAY(),G11,"m")),0)) | I11: =IF(OR(E11="",H11=""),"",E11/MAX(1,H11))
E12: =IF(C12="","",MAX(0,C12-D12)) | F12: =IF(C12="","",IFERROR(MIN(1,D12/C12),0)) | H12: =IF(G12="","",IFERROR(MAX(0,DATEDIF(TODAY(),G12,"m")),0)) | I12: =IF(OR(E12="",H12=""),"",E12/MAX(1,H12))
E13: =IF(C13="","",MAX(0,C13-D13)) | F13: =IF(C13="","",IFERROR(MIN(1,D13/C13),0)) | H13: =IF(G13="","",IFERROR(MAX(0,DATEDIF(TODAY(),G13,"m")),0)) | I13: =IF(OR(E13="",H13=""),"",E13/MAX(1,H13))
E14: =IF(C14="","",MAX(0,C14-D14)) | F14: =IF(C14="","",IFERROR(MIN(1,D14/C14),0)) | H14: =IF(G14="","",IFERROR(MAX(0,DATEDIF(TODAY(),G14,"m")),0)) | I14: =IF(OR(E14="",H14=""),"",E14/MAX(1,H14))
E15: =IF(C15="","",MAX(0,C15-D15)) | F15: =IF(C15="","",IFERROR(MIN(1,D15/C15),0)) | H15: =IF(G15="","",IFERROR(MAX(0,DATEDIF(TODAY(),G15,"m")),0)) | I15: =IF(OR(E15="",H15=""),"",E15/MAX(1,H15))
B16: TOTAL | C16: =SUM(C6:C15) | D16: =SUM(D6:D15) | E16: =SUM(E6:E15) | F16: =IFERROR(D16/C16,0)

Sheet Debt Tracker
B2: Debt Tracker
B3: Payoff time assumes you pay the minimum every month with no new charges.
B5: Debt | C5: Balance | D5: APR % | E5: Min Payment | F5: Months to Payoff | G5: Est. Interest | H5: Payoff Date
B6: Visa | C6: 3200 | D6: 22.9 | E6: 95 | F6: =IF(OR(C6="",E6=""),"",IF(N(D6)=0,ROUNDUP(C6/E6,0),IFERROR(ROUNDUP(NPER(D6/1200,-E6,C6),0),"Never"))) | G6: =IF(ISNUMBER(F6),MAX(0,F6*E6-C6),"") | H6: =IF(ISNUMBER(F6),EDATE(TODAY(),F6),"")
B7: Student Loan | C7: 14800 | D7: 5.5 | E7: 180 | F7: =IF(OR(C7="",E7=""),"",IF(N(D7)=0,ROUNDUP(C7/E7,0),IFERROR(ROUNDUP(NPER(D7/1200,-E7,C7),0),"Never"))) | G7: =IF(ISNUMBER(F7),MAX(0,F7*E7-C7),"") | H7: =IF(ISNUMBER(F7),EDATE(TODAY(),F7),"")
F8: =IF(OR(C8="",E8=""),"",IF(N(D8)=0,ROUNDUP(C8/E8,0),IFERROR(ROUNDUP(NPER(D8/1200,-E8,C8),0),"Never"))) | G8: =IF(ISNUMBER(F8),MAX(0,F8*E8-C8),"") | H8: =IF(ISNUMBER(F8),EDATE(TODAY(),F8),"")
F9: =IF(OR(C9="",E9=""),"",IF(N(D9)=0,ROUNDUP(C9/E9,0),IFERROR(ROUNDUP(NPER(D9/1200,-E9,C9),0),"Never"))) | G9: =IF(ISNUMBER(F9),MAX(0,F9*E9-C9),"") | H9: =IF(ISNUMBER(F9),EDATE(TODAY(),F9),"")
F10: =IF(OR(C10="",E10=""),"",IF(N(D10)=0,ROUNDUP(C10/E10,0),IFERROR(ROUNDUP(NPER(D10/1200,-E10,C10),0),"Never"))) | G10: =IF(ISNUMBER(F10),MAX(0,F10*E10-C10),"") | H10: =IF(ISNUMBER(F10),EDATE(TODAY(),F10),"")
F11: =IF(OR(C11="",E11=""),"",IF(N(D11)=0,ROUNDUP(C11/E11,0),IFERROR(ROUNDUP(NPER(D11/1200,-E11,C11),0),"Never"))) | G11: =IF(ISNUMBER(F11),MAX(0,F11*E11-C11),"") | H11: =IF(ISNUMBER(F11),EDATE(TODAY(),F11),"")
F12: =IF(OR(C12="",E12=""),"",IF(N(D12)=0,ROUNDUP(C12/E12,0),IFERROR(ROUNDUP(NPER(D12/1200,-E12,C12),0),"Never"))) | G12: =IF(ISNUMBER(F12),MAX(0,F12*E12-C12),"") | H12: =IF(ISNUMBER(F12),EDATE(TODAY(),F12),"")
F13: =IF(OR(C13="",E13=""),"",IF(N(D13)=0,ROUNDUP(C13/E13,0),IFERROR(ROUNDUP(NPER(D13/1200,-E13,C13),0),"Never"))) | G13: =IF(ISNUMBER(F13),MAX(0,F13*E13-C13),"") | H13: =IF(ISNUMBER(F13),EDATE(TODAY(),F13),"")
F14: =IF(OR(C14="",E14=""),"",IF(N(D14)=0,ROUNDUP(C14/E14,0),IFERROR(ROUNDUP(NPER(D14/1200,-E14,C14),0),"Never"))) | G14: =IF(ISNUMBER(F14),MAX(0,F14*E14-C14),"") | H14: =IF(ISNUMBER(F14),EDATE(TODAY(),F14),"")
F15: =IF(OR(C15="",E15=""),"",IF(N(D15)=0,ROUNDUP(C15/E15,0),IFERROR(ROUNDUP(NPER(D15/1200,-E15,C15),0),"Never"))) | G15: =IF(ISNUMBER(F15),MAX(0,F15*E15-C15),"") | H15: =IF(ISNUMBER(F15),EDATE(TODAY(),F15),"")
B16: TOTAL | C16: =SUM(C6:C15) | E16: =SUM(E6:E15)

Sheet Lists
A1: Expense Categories | B1: Types | C1: Income Categories
A2: Housing | B2: Bill | C2: Primary
A3: Utilities | B3: Expense | C3: Side Income
A4: Transportation | C4: Bonus
A5: Food | C5: Interest
A6: Insurance | C6: Gifts
A7: Health | C7: Refunds
A8: Debt Payments | C8: Other
A9: Subscriptions
A10: Entertainment
A11: Personal
A12: Savings
A13: Giving
A14: Other
